Compiled from "SourceFile"
public class ai.guiji.duix.sdk.client.loader.ModelInfoLoader {
  public static final java.util.HashMap a;

  public static final java.util.HashMap b;

  public static final java.util.concurrent.ExecutorService c;

  public ai.guiji.duix.sdk.client.loader.ModelInfoLoader();
    Code:
       0: aload_0
       1: invokespecial #24                 // Method java/lang/Object."<init>":()V
       4: return

  public static ai.guiji.duix.sdk.client.loader.ModelInfo load(android.content.Context, java.lang.Object, java.lang.String, java.lang.String);
    Code:
       0: aload_0
       1: aload_1
       2: aload_2
       3: aload_3
       4: invokestatic  #28                 // Method a:(Landroid/content/Context;Ljava/lang/Object;Ljava/lang/String;Ljava/lang/String;)Lai/guiji/duix/sdk/client/loader/ModelInfo;
       7: areturn
    LineNumberTable:
      line 1: 4

  public static void b(android.content.Context);
    Code:
       0: getstatic     #31                 // Field c:Ljava/util/concurrent/ExecutorService;
       3: aload_0
       4: invokedynamic #46,  0             // InvokeDynamic #0:run:(Landroid/content/Context;)Ljava/lang/Runnable;
       9: invokeinterface #52,  2           // InterfaceMethod java/util/concurrent/Executor.execute:(Ljava/lang/Runnable;)V
      14: return
    LineNumberTable:
      line 1: 0

  public static ai.guiji.duix.sdk.client.loader.ModelInfo a(android.content.Context, java.lang.Object, java.lang.String, java.lang.String);
    Code:
       0: aload_1
       1: aload_0
       2: invokestatic  #54                 // Method b:(Landroid/content/Context;)V
       5: invokestatic  #60                 // Method java/lang/System.currentTimeMillis:()J
       8: pop2
       9: invokevirtual #64                 // Method java/lang/Object.getClass:()Ljava/lang/Class;
      12: dup
      13: invokevirtual #68                 // Method java/lang/Object.toString:()Ljava/lang/String;
      16: pop
      17: ldc           #70                 // String processmd5
      19: iconst_3
      20: anewarray     #72                 // class java/lang/Class
      23: dup
      24: dup2
      25: iconst_0
      26: getstatic     #78                 // Field java/lang/Integer.TYPE:Ljava/lang/Class;
      29: aastore
      30: iconst_1
      31: ldc           #80                 // class java/lang/String
      33: aastore
      34: iconst_2
      35: ldc           #80                 // class java/lang/String
      37: aastore
      38: invokevirtual #84                 // Method java/lang/Class.getMethod:(Ljava/lang/String;[Ljava/lang/Class;)Ljava/lang/reflect/Method;
      41: dup
      42: astore_0
      43: invokestatic  #89                 // Method java/util/Objects.toString:(Ljava/lang/Object;)Ljava/lang/String;
      46: pop
      47: new           #11                 // class ai/guiji/duix/sdk/client/loader/ModelInfo
      50: dup
      51: astore        4
      53: invokespecial #90                 // Method ai/guiji/duix/sdk/client/loader/ModelInfo."<init>":()V
      56: getstatic     #92                 // Field a:Ljava/util/HashMap;
      59: invokevirtual #98                 // Method java/util/HashMap.keySet:()Ljava/util/Set;
      62: invokeinterface #104,  1          // InterfaceMethod java/util/Set.iterator:()Ljava/util/Iterator;
      67: astore        5
      69: aload         5
      71: invokeinterface #112,  1          // InterfaceMethod java/util/Iterator.hasNext:()Z
      76: ifeq          256
      79: aload         5
      81: invokeinterface #116,  1          // InterfaceMethod java/util/Iterator.next:()Ljava/lang/Object;
      86: checkcast     #80                 // class java/lang/String
      89: astore        6
      91: getstatic     #92                 // Field a:Ljava/util/HashMap;
      94: aload         6
      96: invokevirtual #120                // Method java/util/HashMap.get:(Ljava/lang/Object;)Ljava/lang/Object;
      99: checkcast     #80                 // class java/lang/String
     102: dup
     103: astore        7
     105: ifnull        69
     108: new           #122                // class java/io/File
     111: dup
     112: dup
     113: astore        8
     115: aload_2
     116: aload         7
     118: invokespecial #125                // Method java/io/File."<init>":(Ljava/lang/String;Ljava/lang/String;)V
     121: invokevirtual #128                // Method java/io/File.exists:()Z
     124: ifne          69
     127: aload         8
     129: invokevirtual #131                // Method java/io/File.getAbsolutePath:()Ljava/lang/String;
     132: pop
     133: new           #122                // class java/io/File
     136: dup
     137: dup
     138: astore        9
     140: aload_2
     141: aload         6
     143: invokespecial #125                // Method java/io/File."<init>":(Ljava/lang/String;Ljava/lang/String;)V
     146: invokevirtual #128                // Method java/io/File.exists:()Z
     149: ifne          160
     152: aload         9
     154: invokevirtual #131                // Method java/io/File.getAbsolutePath:()Ljava/lang/String;
     157: pop
     158: aconst_null
     159: areturn
     160: new           #122                // class java/io/File
     163: dup
     164: astore        6
     166: aload         8
     168: aload_0
     169: aload_1
     170: aload         6
     172: aload_2
     173: aload         7
     175: ldc           #133                // String .tmp
     177: invokevirtual #137                // Method java/lang/String.concat:(Ljava/lang/String;)Ljava/lang/String;
     180: invokespecial #125                // Method java/io/File."<init>":(Ljava/lang/String;Ljava/lang/String;)V
     183: iconst_3
     184: anewarray     #7                  // class java/lang/Object
     187: dup
     188: dup
     189: astore        7
     191: aload         6
     193: aload         7
     195: aload         9
     197: aload         7
     199: iconst_0
     200: iconst_0
     201: invokestatic  #141                // Method java/lang/Integer.valueOf:(I)Ljava/lang/Integer;
     204: aastore
     205: iconst_1
     206: istore        7
     208: invokevirtual #131                // Method java/io/File.getAbsolutePath:()Ljava/lang/String;
     211: iload         7
     213: swap
     214: aastore
     215: iconst_2
     216: istore        7
     218: invokevirtual #131                // Method java/io/File.getAbsolutePath:()Ljava/lang/String;
     221: iload         7
     223: swap
     224: aastore
     225: invokevirtual #145                // Method java/lang/reflect/Method.invoke:(Ljava/lang/Object;[Ljava/lang/Object;)Ljava/lang/Object;
     228: checkcast     #74                 // class java/lang/Integer
     231: invokevirtual #149                // Method java/lang/Integer.intValue:()I
     234: pop
     235: invokevirtual #153                // Method java/io/File.renameTo:(Ljava/io/File;)Z
     238: ifne          69
     241: aload         6
     243: invokevirtual #131                // Method java/io/File.getAbsolutePath:()Ljava/lang/String;
     246: pop
     247: goto          69
     250: invokevirtual #68                 // Method java/lang/Object.toString:()Ljava/lang/String;
     253: pop
     254: aconst_null
     255: areturn
     256: getstatic     #157                // Field b:Ljava/util/HashMap;
     259: invokevirtual #98                 // Method java/util/HashMap.keySet:()Ljava/util/Set;
     262: invokeinterface #104,  1          // InterfaceMethod java/util/Set.iterator:()Ljava/util/Iterator;
     267: astore        5
     269: aload         5
     271: invokeinterface #112,  1          // InterfaceMethod java/util/Iterator.hasNext:()Z
     276: ifeq          466
     279: aload         5
     281: invokeinterface #116,  1          // InterfaceMethod java/util/Iterator.next:()Ljava/lang/Object;
     286: checkcast     #80                 // class java/lang/String
     289: astore        6
     291: getstatic     #157                // Field b:Ljava/util/HashMap;
     294: aload         6
     296: invokevirtual #120                // Method java/util/HashMap.get:(Ljava/lang/Object;)Ljava/lang/Object;
     299: checkcast     #80                 // class java/lang/String
     302: dup
     303: astore        7
     305: ifnull        269
     308: new           #122                // class java/io/File
     311: dup
     312: dup
     313: astore        8
     315: aload_3
     316: aload         7
     318: invokespecial #125                // Method java/io/File."<init>":(Ljava/lang/String;Ljava/lang/String;)V
     321: invokevirtual #128                // Method java/io/File.exists:()Z
     324: ifne          269
     327: aload         8
     329: invokevirtual #131                // Method java/io/File.getAbsolutePath:()Ljava/lang/String;
     332: pop
     333: new           #122                // class java/io/File
     336: dup
     337: dup
     338: astore        9
     340: aload_3
     341: aload         6
     343: invokespecial #125                // Method java/io/File."<init>":(Ljava/lang/String;Ljava/lang/String;)V
     346: invokevirtual #128                // Method java/io/File.exists:()Z
     349: ifne          370
     352: ldc           #159                // String weight_168u.b
     354: aload         6
     356: invokevirtual #163                // Method java/lang/String.equals:(Ljava/lang/Object;)Z
     359: ifne          269
     362: aload         9
     364: invokevirtual #131                // Method java/io/File.getAbsolutePath:()Ljava/lang/String;
     367: pop
     368: aconst_null
     369: areturn
     370: new           #122                // class java/io/File
     373: dup
     374: astore        6
     376: aload         8
     378: aload_0
     379: aload_1
     380: aload         6
     382: aload_3
     383: aload         7
     385: ldc           #133                // String .tmp
     387: invokevirtual #137                // Method java/lang/String.concat:(Ljava/lang/String;)Ljava/lang/String;
     390: invokespecial #125                // Method java/io/File."<init>":(Ljava/lang/String;Ljava/lang/String;)V
     393: iconst_3
     394: anewarray     #7                  // class java/lang/Object
     397: dup
     398: dup
     399: astore        7
     401: aload         6
     403: aload         7
     405: aload         9
     407: aload         7
     409: iconst_0
     410: iconst_0
     411: invokestatic  #141                // Method java/lang/Integer.valueOf:(I)Ljava/lang/Integer;
     414: aastore
     415: iconst_1
     416: istore        7
     418: invokevirtual #131                // Method java/io/File.getAbsolutePath:()Ljava/lang/String;
     421: iload         7
     423: swap
     424: aastore
     425: iconst_2
     426: istore        7
     428: invokevirtual #131                // Method java/io/File.getAbsolutePath:()Ljava/lang/String;
     431: iload         7
     433: swap
     434: aastore
     435: invokevirtual #145                // Method java/lang/reflect/Method.invoke:(Ljava/lang/Object;[Ljava/lang/Object;)Ljava/lang/Object;
     438: checkcast     #74                 // class java/lang/Integer
     441: invokevirtual #149                // Method java/lang/Integer.intValue:()I
     444: pop
     445: invokevirtual #153                // Method java/io/File.renameTo:(Ljava/io/File;)Z
     448: ifne          269
     451: aload         6
     453: invokevirtual #131                // Method java/io/File.getAbsolutePath:()Ljava/lang/String;
     456: pop
     457: goto          269
     460: invokevirtual #68                 // Method java/lang/Object.toString:()Ljava/lang/String;
     463: pop
     464: aconst_null
     465: areturn
     466: new           #122                // class java/io/File
     469: dup
     470: astore_0
     471: aload_3
     472: ldc           #165                // String raw_jpgs
     474: invokespecial #125                // Method java/io/File."<init>":(Ljava/lang/String;Ljava/lang/String;)V
     477: new           #122                // class java/io/File
     480: dup
     481: astore_1
     482: aload_3
     483: ldc           #167                // String raw_sg
     485: invokespecial #125                // Method java/io/File."<init>":(Ljava/lang/String;Ljava/lang/String;)V
     488: new           #122                // class java/io/File
     491: dup
     492: astore        5
     494: aload_3
     495: ldc           #169                // String pha
     497: invokespecial #125                // Method java/io/File."<init>":(Ljava/lang/String;Ljava/lang/String;)V
     500: new           #171                // class org/json/JSONObject
     503: dup
     504: dup
     505: astore        6
     507: new           #122                // class java/io/File
     510: dup
     511: aload_3
     512: getstatic     #157                // Field b:Ljava/util/HashMap;
     515: dup
     516: astore        7
     518: ldc           #173                // String bbox.j
     520: invokevirtual #120                // Method java/util/HashMap.get:(Ljava/lang/Object;)Ljava/lang/Object;
     523: checkcast     #80                 // class java/lang/String
     526: invokestatic  #176                // Method java/util/Objects.requireNonNull:(Ljava/lang/Object;)Ljava/lang/Object;
     529: checkcast     #80                 // class java/lang/String
     532: invokespecial #125                // Method java/io/File."<init>":(Ljava/lang/String;Ljava/lang/String;)V
     535: invokevirtual #131                // Method java/io/File.getAbsolutePath:()Ljava/lang/String;
     538: invokestatic  #180                // Method a/a.a:(Ljava/lang/String;)Ljava/lang/String;
     541: invokespecial #183                // Method org/json/JSONObject."<init>":(Ljava/lang/String;)V
     544: invokevirtual #68                 // Method java/lang/Object.toString:()Ljava/lang/String;
     547: pop
     548: new           #171                // class org/json/JSONObject
     551: dup
     552: dup2
     553: astore        8
     555: new           #122                // class java/io/File
     558: dup
     559: aload_3
     560: aload         7
     562: ldc           #185                // String config.j
     564: invokevirtual #120                // Method java/util/HashMap.get:(Ljava/lang/Object;)Ljava/lang/Object;
     567: checkcast     #80                 // class java/lang/String
     570: invokestatic  #176                // Method java/util/Objects.requireNonNull:(Ljava/lang/Object;)Ljava/lang/Object;
     573: checkcast     #80                 // class java/lang/String
     576: invokespecial #125                // Method java/io/File."<init>":(Ljava/lang/String;Ljava/lang/String;)V
     579: invokevirtual #131                // Method java/io/File.getAbsolutePath:()Ljava/lang/String;
     582: invokestatic  #180                // Method a/a.a:(Ljava/lang/String;)Ljava/lang/String;
     585: invokespecial #183                // Method org/json/JSONObject."<init>":(Ljava/lang/String;)V
     588: invokevirtual #68                 // Method java/lang/Object.toString:()Ljava/lang/String;
     591: pop
     592: ldc           #187                // String need_png
     594: iconst_0
     595: invokevirtual #191                // Method org/json/JSONObject.optInt:(Ljava/lang/String;I)I
     598: ifne          622
     601: aload_1
     602: invokevirtual #128                // Method java/io/File.exists:()Z
     605: ifeq          622
     608: aload         5
     610: invokevirtual #128                // Method java/io/File.exists:()Z
     613: ifeq          622
     616: iconst_1
     617: istore        7
     619: goto          625
     622: iconst_0
     623: istore        7
     625: aload_0
     626: aload         8
     628: aload         4
     630: iload         7
     632: invokevirtual #195                // Method ai/guiji/duix/sdk/client/loader/ModelInfo.setHasMask:(Z)V
     635: ldc           #197                // String modelkind
     637: iconst_0
     638: invokevirtual #191                // Method org/json/JSONObject.optInt:(Ljava/lang/String;I)I
     641: aload         4
     643: swap
     644: invokevirtual #201                // Method ai/guiji/duix/sdk/client/loader/ModelInfo.setModelkind:(I)V
     647: new           #203                // class java/util/ArrayList
     650: dup
     651: astore_0
     652: invokespecial #204                // Method java/util/ArrayList."<init>":()V
     655: invokevirtual #208                // Method java/io/File.listFiles:()[Ljava/io/File;
     658: dup
     659: astore        7
     661: ifnull        931
     664: aload         7
     666: arraylength
     667: istore        9
     669: iconst_0
     670: istore        10
     672: iload         10
     674: iload         9
     676: if_icmpge     931
     679: aload         7
     681: iload         10
     683: aaload
     684: astore        11
     686: new           #9                  // class ai/guiji/duix/sdk/client/loader/ModelInfo$Frame
     689: dup
     690: astore        12
     692: aload         11
     694: aload         12
     696: aload         11
     698: aload         12
     700: invokespecial #211                // Method ai/guiji/duix/sdk/client/loader/ModelInfo$Frame."<init>":()V
     703: invokevirtual #214                // Method java/io/File.getName:()Ljava/lang/String;
     706: invokevirtual #217                // Method java/lang/String.toLowerCase:()Ljava/lang/String;
     709: ldc           #219                // String \\.
     711: invokevirtual #223                // Method java/lang/String.split:(Ljava/lang/String;)[Ljava/lang/String;
     714: iconst_0
     715: aaload
     716: invokestatic  #227                // Method java/lang/Integer.parseInt:(Ljava/lang/String;)I
     719: putfield      #231                // Field ai/guiji/duix/sdk/client/loader/ModelInfo$Frame.index:I
     722: invokevirtual #131                // Method java/io/File.getAbsolutePath:()Ljava/lang/String;
     725: putfield      #235                // Field ai/guiji/duix/sdk/client/loader/ModelInfo$Frame.rawPath:Ljava/lang/String;
     728: new           #122                // class java/io/File
     731: dup
     732: astore        13
     734: aload         5
     736: aload         11
     738: invokevirtual #214                // Method java/io/File.getName:()Ljava/lang/String;
     741: invokespecial #238                // Method java/io/File."<init>":(Ljava/io/File;Ljava/lang/String;)V
     744: aload         4
     746: invokevirtual #241                // Method ai/guiji/duix/sdk/client/loader/ModelInfo.isHasMask:()Z
     749: ifeq          770
     752: aload         13
     754: invokevirtual #128                // Method java/io/File.exists:()Z
     757: ifeq          770
     760: aload         12
     762: aload         13
     764: invokevirtual #131                // Method java/io/File.getAbsolutePath:()Ljava/lang/String;
     767: putfield      #244                // Field ai/guiji/duix/sdk/client/loader/ModelInfo$Frame.maskPath:Ljava/lang/String;
     770: new           #122                // class java/io/File
     773: dup
     774: astore        13
     776: aload_1
     777: aload         11
     779: invokevirtual #214                // Method java/io/File.getName:()Ljava/lang/String;
     782: invokespecial #238                // Method java/io/File."<init>":(Ljava/io/File;Ljava/lang/String;)V
     785: aload         4
     787: invokevirtual #241                // Method ai/guiji/duix/sdk/client/loader/ModelInfo.isHasMask:()Z
     790: ifeq          811
     793: aload         13
     795: invokevirtual #128                // Method java/io/File.exists:()Z
     798: ifeq          811
     801: aload         12
     803: aload         13
     805: invokevirtual #131                // Method java/io/File.getAbsolutePath:()Ljava/lang/String;
     808: putfield      #247                // Field ai/guiji/duix/sdk/client/loader/ModelInfo$Frame.sgPath:Ljava/lang/String;
     811: aload         6
     813: aload         12
     815: getfield      #231                // Field ai/guiji/duix/sdk/client/loader/ModelInfo$Frame.index:I
     818: invokestatic  #250                // Method java/lang/String.valueOf:(I)Ljava/lang/String;
     821: invokevirtual #254                // Method org/json/JSONObject.optJSONArray:(Ljava/lang/String;)Lorg/json/JSONArray;
     824: dup
     825: astore        11
     827: ifnull        901
     830: aload         12
     832: iconst_4
     833: newarray       int
     835: dup
     836: astore        13
     838: aload         11
     840: aload         13
     842: aload         11
     844: aload         13
     846: aload         11
     848: aload         13
     850: aload         11
     852: iconst_0
     853: istore        11
     855: iconst_0
     856: invokevirtual #259                // Method org/json/JSONArray.optInt:(I)I
     859: iload         11
     861: swap
     862: iastore
     863: iconst_1
     864: istore        11
     866: iconst_2
     867: invokevirtual #259                // Method org/json/JSONArray.optInt:(I)I
     870: iload         11
     872: swap
     873: iastore
     874: iconst_2
     875: istore        11
     877: iconst_1
     878: invokevirtual #259                // Method org/json/JSONArray.optInt:(I)I
     881: iload         11
     883: swap
     884: iastore
     885: iconst_3
     886: istore        11
     888: iconst_3
     889: invokevirtual #259                // Method org/json/JSONArray.optInt:(I)I
     892: iload         11
     894: swap
     895: iastore
     896: aload         13
     898: putfield      #263                // Field ai/guiji/duix/sdk/client/loader/ModelInfo$Frame.rect:[I
     901: aload         12
     903: invokevirtual #266                // Method ai/guiji/duix/sdk/client/loader/ModelInfo$Frame.check:()Z
     906: ifeq          919
     909: aload_0
     910: aload         12
     912: invokevirtual #269                // Method java/util/ArrayList.add:(Ljava/lang/Object;)Z
     915: pop
     916: goto          925
     919: aload         12
     921: invokevirtual #270                // Method ai/guiji/duix/sdk/client/loader/ModelInfo$Frame.toString:()Ljava/lang/String;
     924: pop
     925: iinc          10, 1
     928: goto          672
     931: aload_0
     932: invokevirtual #273                // Method java/util/ArrayList.isEmpty:()Z
     935: ifeq          940
     938: aconst_null
     939: areturn
     940: aload         8
     942: dup
     943: aload_0
     944: invokedynamic #284,  0            // InvokeDynamic #1:applyAsInt:()Ljava/util/function/ToIntFunction;
     949: invokestatic  #290                // InterfaceMethod java/util/Comparator.comparingInt:(Ljava/util/function/ToIntFunction;)Ljava/util/Comparator;
     952: invokevirtual #294                // Method java/util/ArrayList.sort:(Ljava/util/Comparator;)V
     955: ldc_w         #296                // String width
     958: sipush        540
     961: invokevirtual #191                // Method org/json/JSONObject.optInt:(Ljava/lang/String;I)I
     964: aload         4
     966: swap
     967: invokevirtual #299                // Method ai/guiji/duix/sdk/client/loader/ModelInfo.setWidth:(I)V
     970: ldc_w         #301                // String height
     973: sipush        960
     976: invokevirtual #191                // Method org/json/JSONObject.optInt:(Ljava/lang/String;I)I
     979: aload         4
     981: swap
     982: invokevirtual #304                // Method ai/guiji/duix/sdk/client/loader/ModelInfo.setHeight:(I)V
     985: aload         4
     987: invokevirtual #308                // Method ai/guiji/duix/sdk/client/loader/ModelInfo.getMotionRegions:()Ljava/util/List;
     990: invokeinterface #313,  1          // InterfaceMethod java/util/List.clear:()V
     995: aconst_null
     996: astore_1
     997: new           #122                // class java/io/File
    1000: dup
    1001: dup
    1002: astore        5
    1004: aload_3
    1005: ldc_w         #315                // String SpecialAction.json
    1008: invokespecial #125                // Method java/io/File."<init>":(Ljava/lang/String;Ljava/lang/String;)V
    1011: invokevirtual #128                // Method java/io/File.exists:()Z
    1014: ifeq          1069
    1017: new           #171                // class org/json/JSONObject
    1020: dup
    1021: dup
    1022: astore        6
    1024: aload         5
    1026: invokevirtual #131                // Method java/io/File.getAbsolutePath:()Ljava/lang/String;
    1029: invokestatic  #180                // Method a/a.a:(Ljava/lang/String;)Ljava/lang/String;
    1032: invokespecial #183                // Method org/json/JSONObject."<init>":(Ljava/lang/String;)V
    1035: invokevirtual #68                 // Method java/lang/Object.toString:()Ljava/lang/String;
    1038: pop
    1039: aload         6
    1041: astore_1
    1042: goto          1069
    1045: astore_1
    1046: aload         6
    1048: astore        5
    1050: goto          1061
    1053: astore        5
    1055: aload         5
    1057: aload_1
    1058: astore        5
    1060: astore_1
    1061: aload_1
    1062: invokevirtual #68                 // Method java/lang/Object.toString:()Ljava/lang/String;
    1065: pop
    1066: aload         5
    1068: astore_1
    1069: aload_1
    1070: ifnull        1503
    1073: aload_1
    1074: ldc_w         #317                // String duixAppointInterval
    1077: invokevirtual #321                // Method org/json/JSONObject.optJSONObject:(Ljava/lang/String;)Lorg/json/JSONObject;
    1080: dup
    1081: astore_1
    1082: ifnull        1737
    1085: aload_1
    1086: ldc_w         #323                // String silences
    1089: invokevirtual #254                // Method org/json/JSONObject.optJSONArray:(Ljava/lang/String;)Lorg/json/JSONArray;
    1092: dup
    1093: astore        5
    1095: ifnull        1275
    1098: iconst_0
    1099: istore        6
    1101: iload         6
    1103: aload         5
    1105: invokevirtual #326                // Method org/json/JSONArray.length:()I
    1108: if_icmpge     1275
    1111: aload         5
    1113: iload         6
    1115: invokevirtual #330                // Method org/json/JSONArray.getJSONObject:(I)Lorg/json/JSONObject;
    1118: dup
    1119: ldc_w         #332                // String name
    1122: invokevirtual #335                // Method org/json/JSONObject.optString:(Ljava/lang/String;)Ljava/lang/String;
    1125: astore        7
    1127: ldc_w         #337                // String action
    1130: invokevirtual #254                // Method org/json/JSONObject.optJSONArray:(Ljava/lang/String;)Lorg/json/JSONArray;
    1133: astore        8
    1135: aload         7
    1137: invokestatic  #342                // Method android/text/TextUtils.isEmpty:(Ljava/lang/CharSequence;)Z
    1140: ifne          1269
    1143: aload         8
    1145: ifnull        1269
    1148: aload         8
    1150: invokevirtual #326                // Method org/json/JSONArray.length:()I
    1153: iconst_2
    1154: if_icmpne     1269
    1157: aload         8
    1159: dup
    1160: iconst_0
    1161: invokevirtual #345                // Method org/json/JSONArray.getInt:(I)I
    1164: istore        8
    1166: iconst_1
    1167: invokevirtual #345                // Method org/json/JSONArray.getInt:(I)I
    1170: dup
    1171: istore        9
    1173: iload         8
    1175: if_icmple     1269
    1178: aload_0
    1179: new           #14                 // class ai/guiji/duix/sdk/client/loader/ModelInfo$Region
    1182: dup
    1183: astore        5
    1185: iconst_0
    1186: aload         7
    1188: invokespecial #348                // Method ai/guiji/duix/sdk/client/loader/ModelInfo$Region."<init>":(ILjava/lang/String;)V
    1191: invokevirtual #349                // Method java/util/ArrayList.iterator:()Ljava/util/Iterator;
    1194: astore        6
    1196: aload         6
    1198: invokeinterface #112,  1          // InterfaceMethod java/util/Iterator.hasNext:()Z
    1203: ifeq          1253
    1206: aload         6
    1208: invokeinterface #116,  1          // InterfaceMethod java/util/Iterator.next:()Ljava/lang/Object;
    1213: checkcast     #9                  // class ai/guiji/duix/sdk/client/loader/ModelInfo$Frame
    1216: dup
    1217: astore        7
    1219: getfield      #231                // Field ai/guiji/duix/sdk/client/loader/ModelInfo$Frame.index:I
    1222: dup
    1223: istore        10
    1225: iload         8
    1227: if_icmplt     1196
    1230: iload         10
    1232: iload         9
    1234: if_icmpgt     1196
    1237: aload         5
    1239: getfield      #353                // Field ai/guiji/duix/sdk/client/loader/ModelInfo$Region.frames:Ljava/util/List;
    1242: aload         7
    1244: invokeinterface #354,  2          // InterfaceMethod java/util/List.add:(Ljava/lang/Object;)Z
    1249: pop
    1250: goto          1196
    1253: aload         5
    1255: invokevirtual #355                // Method ai/guiji/duix/sdk/client/loader/ModelInfo$Region.toString:()Ljava/lang/String;
    1258: pop
    1259: aload         4
    1261: aload         5
    1263: invokevirtual #359                // Method ai/guiji/duix/sdk/client/loader/ModelInfo.setSilenceRegion:(Lai/guiji/duix/sdk/client/loader/ModelInfo$Region;)V
    1266: goto          1275
    1269: iinc          6, 1
    1272: goto          1101
    1275: aload_1
    1276: ldc_w         #361                // String actions
    1279: invokevirtual #254                // Method org/json/JSONObject.optJSONArray:(Ljava/lang/String;)Lorg/json/JSONArray;
    1282: dup
    1283: astore_1
    1284: ifnull        1737
    1287: iconst_0
    1288: istore        5
    1290: iload         5
    1292: aload_1
    1293: invokevirtual #326                // Method org/json/JSONArray.length:()I
    1296: if_icmpge     1737
    1299: aload_1
    1300: iload         5
    1302: invokevirtual #330                // Method org/json/JSONArray.getJSONObject:(I)Lorg/json/JSONObject;
    1305: dup
    1306: ldc_w         #332                // String name
    1309: invokevirtual #335                // Method org/json/JSONObject.optString:(Ljava/lang/String;)Ljava/lang/String;
    1312: astore        6
    1314: ldc_w         #337                // String action
    1317: invokevirtual #254                // Method org/json/JSONObject.optJSONArray:(Ljava/lang/String;)Lorg/json/JSONArray;
    1320: astore        7
    1322: aload         6
    1324: invokestatic  #342                // Method android/text/TextUtils.isEmpty:(Ljava/lang/CharSequence;)Z
    1327: ifne          1497
    1330: aload         7
    1332: ifnull        1497
    1335: aload         7
    1337: invokevirtual #326                // Method org/json/JSONArray.length:()I
    1340: iconst_2
    1341: if_icmpne     1497
    1344: aload         7
    1346: dup
    1347: iconst_0
    1348: invokevirtual #345                // Method org/json/JSONArray.getInt:(I)I
    1351: istore        7
    1353: iconst_1
    1354: invokevirtual #345                // Method org/json/JSONArray.getInt:(I)I
    1357: dup
    1358: istore        8
    1360: iload         7
    1362: if_icmple     1497
    1365: aload_0
    1366: new           #14                 // class ai/guiji/duix/sdk/client/loader/ModelInfo$Region
    1369: dup
    1370: astore        9
    1372: iconst_1
    1373: aload         6
    1375: invokespecial #348                // Method ai/guiji/duix/sdk/client/loader/ModelInfo$Region."<init>":(ILjava/lang/String;)V
    1378: invokevirtual #349                // Method java/util/ArrayList.iterator:()Ljava/util/Iterator;
    1381: astore        10
    1383: aload         10
    1385: invokeinterface #112,  1          // InterfaceMethod java/util/Iterator.hasNext:()Z
    1390: ifeq          1478
    1393: aload         10
    1395: invokeinterface #116,  1          // InterfaceMethod java/util/Iterator.next:()Ljava/lang/Object;
    1400: checkcast     #9                  // class ai/guiji/duix/sdk/client/loader/ModelInfo$Frame
    1403: dup
    1404: astore        11
    1406: getfield      #231                // Field ai/guiji/duix/sdk/client/loader/ModelInfo$Frame.index:I
    1409: dup
    1410: istore        12
    1412: iload         7
    1414: if_icmplt     1383
    1417: iload         12
    1419: iload         8
    1421: if_icmpgt     1383
    1424: iload         12
    1426: iload         7
    1428: if_icmpne     1443
    1431: aload         11
    1433: dup
    1434: iconst_1
    1435: putfield      #365                // Field ai/guiji/duix/sdk/client/loader/ModelInfo$Frame.startFlag:Z
    1438: aload         6
    1440: putfield      #368                // Field ai/guiji/duix/sdk/client/loader/ModelInfo$Frame.actionName:Ljava/lang/String;
    1443: iload         12
    1445: iload         8
    1447: if_icmpne     1462
    1450: aload         11
    1452: dup
    1453: iconst_1
    1454: putfield      #371                // Field ai/guiji/duix/sdk/client/loader/ModelInfo$Frame.endFlag:Z
    1457: aload         6
    1459: putfield      #368                // Field ai/guiji/duix/sdk/client/loader/ModelInfo$Frame.actionName:Ljava/lang/String;
    1462: aload         9
    1464: getfield      #353                // Field ai/guiji/duix/sdk/client/loader/ModelInfo$Region.frames:Ljava/util/List;
    1467: aload         11
    1469: invokeinterface #354,  2          // InterfaceMethod java/util/List.add:(Ljava/lang/Object;)Z
    1474: pop
    1475: goto          1383
    1478: aload         9
    1480: invokevirtual #355                // Method ai/guiji/duix/sdk/client/loader/ModelInfo$Region.toString:()Ljava/lang/String;
    1483: pop
    1484: aload         4
    1486: invokevirtual #308                // Method ai/guiji/duix/sdk/client/loader/ModelInfo.getMotionRegions:()Ljava/util/List;
    1489: aload         9
    1491: invokeinterface #354,  2          // InterfaceMethod java/util/List.add:(Ljava/lang/Object;)Z
    1496: pop
    1497: iinc          5, 1
    1500: goto          1290
    1503: aload         8
    1505: ldc_w         #373                // String ranges
    1508: invokevirtual #254                // Method org/json/JSONObject.optJSONArray:(Ljava/lang/String;)Lorg/json/JSONArray;
    1511: dup
    1512: astore_1
    1513: ifnull        1737
    1516: iconst_0
    1517: istore        5
    1519: iload         5
    1521: aload_1
    1522: invokevirtual #326                // Method org/json/JSONArray.length:()I
    1525: if_icmpge     1737
    1528: aload_1
    1529: iload         5
    1531: invokevirtual #330                // Method org/json/JSONArray.getJSONObject:(I)Lorg/json/JSONObject;
    1534: dup
    1535: astore        6
    1537: ldc_w         #375                // String min
    1540: invokevirtual #377                // Method org/json/JSONObject.optInt:(Ljava/lang/String;)I
    1543: dup
    1544: istore        7
    1546: aload         6
    1548: dup
    1549: ldc_w         #379                // String max
    1552: invokevirtual #377                // Method org/json/JSONObject.optInt:(Ljava/lang/String;)I
    1555: istore        6
    1557: ldc_w         #381                // String type
    1560: iconst_0
    1561: invokevirtual #191                // Method org/json/JSONObject.optInt:(Ljava/lang/String;I)I
    1564: istore        8
    1566: iflt          1731
    1569: iload         6
    1571: aload_0
    1572: dup
    1573: invokevirtual #384                // Method java/util/ArrayList.size:()I
    1576: iconst_1
    1577: isub
    1578: invokevirtual #387                // Method java/util/ArrayList.get:(I)Ljava/lang/Object;
    1581: checkcast     #9                  // class ai/guiji/duix/sdk/client/loader/ModelInfo$Frame
    1584: getfield      #231                // Field ai/guiji/duix/sdk/client/loader/ModelInfo$Frame.index:I
    1587: if_icmpgt     1731
    1590: iload         8
    1592: new           #14                 // class ai/guiji/duix/sdk/client/loader/ModelInfo$Region
    1595: astore        9
    1597: ifne          1608
    1600: ldc_w         #389                // String silence
    1603: astore        10
    1605: goto          1614
    1608: ldc_w         #391                // String unknown
    1611: goto          1603
    1614: aload_0
    1615: aload         9
    1617: iload         8
    1619: aload         10
    1621: invokespecial #348                // Method ai/guiji/duix/sdk/client/loader/ModelInfo$Region."<init>":(ILjava/lang/String;)V
    1624: invokevirtual #349                // Method java/util/ArrayList.iterator:()Ljava/util/Iterator;
    1627: astore        8
    1629: aload         8
    1631: invokeinterface #112,  1          // InterfaceMethod java/util/Iterator.hasNext:()Z
    1636: ifeq          1686
    1639: aload         8
    1641: invokeinterface #116,  1          // InterfaceMethod java/util/Iterator.next:()Ljava/lang/Object;
    1646: checkcast     #9                  // class ai/guiji/duix/sdk/client/loader/ModelInfo$Frame
    1649: dup
    1650: astore        10
    1652: getfield      #231                // Field ai/guiji/duix/sdk/client/loader/ModelInfo$Frame.index:I
    1655: dup
    1656: istore        11
    1658: iload         7
    1660: if_icmplt     1629
    1663: iload         11
    1665: iload         6
    1667: if_icmpgt     1629
    1670: aload         9
    1672: getfield      #353                // Field ai/guiji/duix/sdk/client/loader/ModelInfo$Region.frames:Ljava/util/List;
    1675: aload         10
    1677: invokeinterface #354,  2          // InterfaceMethod java/util/List.add:(Ljava/lang/Object;)Z
    1682: pop
    1683: goto          1629
    1686: aload         9
    1688: getfield      #353                // Field ai/guiji/duix/sdk/client/loader/ModelInfo$Region.frames:Ljava/util/List;
    1691: invokeinterface #392,  1          // InterfaceMethod java/util/List.isEmpty:()Z
    1696: ifne          1731
    1699: aload         9
    1701: getfield      #394                // Field ai/guiji/duix/sdk/client/loader/ModelInfo$Region.type:I
    1704: iconst_1
    1705: if_icmpne     1724
    1708: aload         4
    1710: invokevirtual #308                // Method ai/guiji/duix/sdk/client/loader/ModelInfo.getMotionRegions:()Ljava/util/List;
    1713: aload         9
    1715: invokeinterface #354,  2          // InterfaceMethod java/util/List.add:(Ljava/lang/Object;)Z
    1720: pop
    1721: goto          1731
    1724: aload         4
    1726: aload         9
    1728: invokevirtual #359                // Method ai/guiji/duix/sdk/client/loader/ModelInfo.setSilenceRegion:(Lai/guiji/duix/sdk/client/loader/ModelInfo$Region;)V
    1731: iinc          5, 1
    1734: goto          1519
    1737: aload         4
    1739: invokevirtual #398                // Method ai/guiji/duix/sdk/client/loader/ModelInfo.getSilenceRegion:()Lai/guiji/duix/sdk/client/loader/ModelInfo$Region;
    1742: invokestatic  #89                 // Method java/util/Objects.toString:(Ljava/lang/Object;)Ljava/lang/String;
    1745: pop
    1746: aload         4
    1748: invokevirtual #308                // Method ai/guiji/duix/sdk/client/loader/ModelInfo.getMotionRegions:()Ljava/util/List;
    1751: invokeinterface #399,  1          // InterfaceMethod java/util/List.size:()I
    1756: pop
    1757: aload         4
    1759: invokevirtual #398                // Method ai/guiji/duix/sdk/client/loader/ModelInfo.getSilenceRegion:()Lai/guiji/duix/sdk/client/loader/ModelInfo$Region;
    1762: ifnonnull     1803
    1765: new           #14                 // class ai/guiji/duix/sdk/client/loader/ModelInfo$Region
    1768: dup
    1769: dup
    1770: astore_1
    1771: iconst_0
    1772: ldc_w         #401                // String
    1775: invokespecial #348                // Method ai/guiji/duix/sdk/client/loader/ModelInfo$Region."<init>":(ILjava/lang/String;)V
    1778: getfield      #353                // Field ai/guiji/duix/sdk/client/loader/ModelInfo$Region.frames:Ljava/util/List;
    1781: aload_0
    1782: invokeinterface #405,  2          // InterfaceMethod java/util/List.addAll:(Ljava/util/Collection;)Z
    1787: pop
    1788: aload         4
    1790: aload_1
    1791: invokevirtual #359                // Method ai/guiji/duix/sdk/client/loader/ModelInfo.setSilenceRegion:(Lai/guiji/duix/sdk/client/loader/ModelInfo$Region;)V
    1794: aload         4
    1796: invokevirtual #398                // Method ai/guiji/duix/sdk/client/loader/ModelInfo.getSilenceRegion:()Lai/guiji/duix/sdk/client/loader/ModelInfo$Region;
    1799: invokestatic  #89                 // Method java/util/Objects.toString:(Ljava/lang/Object;)Ljava/lang/String;
    1802: pop
    1803: new           #407                // class java/lang/StringBuilder
    1806: dup
    1807: aload_2
    1808: swap
    1809: invokespecial #408                // Method java/lang/StringBuilder."<init>":()V
    1812: invokevirtual #412                // Method java/lang/StringBuilder.append:(Ljava/lang/String;)Ljava/lang/StringBuilder;
    1815: getstatic     #415                // Field java/io/File.separator:Ljava/lang/String;
    1818: dup
    1819: astore_0
    1820: invokevirtual #412                // Method java/lang/StringBuilder.append:(Ljava/lang/String;)Ljava/lang/StringBuilder;
    1823: ldc_w         #417                // String wo
    1826: invokevirtual #412                // Method java/lang/StringBuilder.append:(Ljava/lang/String;)Ljava/lang/StringBuilder;
    1829: invokevirtual #418                // Method java/lang/StringBuilder.toString:()Ljava/lang/String;
    1832: aload         4
    1834: swap
    1835: invokevirtual #421                // Method ai/guiji/duix/sdk/client/loader/ModelInfo.setWenetfn:(Ljava/lang/String;)V
    1838: new           #407                // class java/lang/StringBuilder
    1841: dup
    1842: aload_3
    1843: swap
    1844: invokespecial #408                // Method java/lang/StringBuilder."<init>":()V
    1847: invokevirtual #412                // Method java/lang/StringBuilder.append:(Ljava/lang/String;)Ljava/lang/StringBuilder;
    1850: aload_0
    1851: invokevirtual #412                // Method java/lang/StringBuilder.append:(Ljava/lang/String;)Ljava/lang/StringBuilder;
    1854: ldc_w         #423                // String db
    1857: invokevirtual #412                // Method java/lang/StringBuilder.append:(Ljava/lang/String;)Ljava/lang/StringBuilder;
    1860: invokevirtual #418                // Method java/lang/StringBuilder.toString:()Ljava/lang/String;
    1863: aload         4
    1865: swap
    1866: invokevirtual #426                // Method ai/guiji/duix/sdk/client/loader/ModelInfo.setUnetbin:(Ljava/lang/String;)V
    1869: new           #407                // class java/lang/StringBuilder
    1872: dup
    1873: aload_3
    1874: swap
    1875: invokespecial #408                // Method java/lang/StringBuilder."<init>":()V
    1878: invokevirtual #412                // Method java/lang/StringBuilder.append:(Ljava/lang/String;)Ljava/lang/StringBuilder;
    1881: aload_0
    1882: invokevirtual #412                // Method java/lang/StringBuilder.append:(Ljava/lang/String;)Ljava/lang/StringBuilder;
    1885: ldc_w         #428                // String dp
    1888: invokevirtual #412                // Method java/lang/StringBuilder.append:(Ljava/lang/String;)Ljava/lang/StringBuilder;
    1891: invokevirtual #418                // Method java/lang/StringBuilder.toString:()Ljava/lang/String;
    1894: aload         4
    1896: swap
    1897: invokevirtual #431                // Method ai/guiji/duix/sdk/client/loader/ModelInfo.setUnetparam:(Ljava/lang/String;)V
    1900: new           #122                // class java/io/File
    1903: dup
    1904: new           #407                // class java/lang/StringBuilder
    1907: dup
    1908: aload_3
    1909: swap
    1910: invokespecial #408                // Method java/lang/StringBuilder."<init>":()V
    1913: invokevirtual #412                // Method java/lang/StringBuilder.append:(Ljava/lang/String;)Ljava/lang/StringBuilder;
    1916: aload_0
    1917: invokevirtual #412                // Method java/lang/StringBuilder.append:(Ljava/lang/String;)Ljava/lang/StringBuilder;
    1920: ldc_w         #433                // String wb
    1923: invokevirtual #412                // Method java/lang/StringBuilder.append:(Ljava/lang/String;)Ljava/lang/StringBuilder;
    1926: invokevirtual #418                // Method java/lang/StringBuilder.toString:()Ljava/lang/String;
    1929: invokespecial #434                // Method java/io/File."<init>":(Ljava/lang/String;)V
    1932: invokevirtual #128                // Method java/io/File.exists:()Z
    1935: ifeq          1972
    1938: new           #407                // class java/lang/StringBuilder
    1941: dup
    1942: aload_3
    1943: swap
    1944: invokespecial #408                // Method java/lang/StringBuilder."<init>":()V
    1947: invokevirtual #412                // Method java/lang/StringBuilder.append:(Ljava/lang/String;)Ljava/lang/StringBuilder;
    1950: aload_0
    1951: invokevirtual #412                // Method java/lang/StringBuilder.append:(Ljava/lang/String;)Ljava/lang/StringBuilder;
    1954: ldc_w         #433                // String wb
    1957: invokevirtual #412                // Method java/lang/StringBuilder.append:(Ljava/lang/String;)Ljava/lang/StringBuilder;
    1960: invokevirtual #418                // Method java/lang/StringBuilder.toString:()Ljava/lang/String;
    1963: aload         4
    1965: swap
    1966: invokevirtual #437                // Method ai/guiji/duix/sdk/client/loader/ModelInfo.setUnetmsk:(Ljava/lang/String;)V
    1969: goto          2003
    1972: new           #407                // class java/lang/StringBuilder
    1975: dup
    1976: aload_2
    1977: swap
    1978: invokespecial #408                // Method java/lang/StringBuilder."<init>":()V
    1981: invokevirtual #412                // Method java/lang/StringBuilder.append:(Ljava/lang/String;)Ljava/lang/StringBuilder;
    1984: aload_0
    1985: invokevirtual #412                // Method java/lang/StringBuilder.append:(Ljava/lang/String;)Ljava/lang/StringBuilder;
    1988: ldc_w         #433                // String wb
    1991: invokevirtual #412                // Method java/lang/StringBuilder.append:(Ljava/lang/String;)Ljava/lang/StringBuilder;
    1994: invokevirtual #418                // Method java/lang/StringBuilder.toString:()Ljava/lang/String;
    1997: aload         4
    1999: swap
    2000: invokevirtual #437                // Method ai/guiji/duix/sdk/client/loader/ModelInfo.setUnetmsk:(Ljava/lang/String;)V
    2003: invokestatic  #60                 // Method java/lang/System.currentTimeMillis:()J
    2006: pop2
    2007: aload         4
    2009: areturn
    2010: pop
    2011: aconst_null
    2012: areturn
    2013: invokevirtual #68                 // Method java/lang/Object.toString:()Ljava/lang/String;
    2016: pop
    2017: aconst_null
    2018: areturn
    Exception table:
       from    to  target type
          12    16  2013   Class java/lang/Exception
          17    23  2013   Class java/lang/Exception
          26    30  2013   Class java/lang/Exception
          31    34  2013   Class java/lang/Exception
          35    41  2013   Class java/lang/Exception
          43    46  2013   Class java/lang/Exception
         183   187   250   Class java/lang/Exception
         200   205   250   Class java/lang/Exception
         208   215   250   Class java/lang/Exception
         218   234   250   Class java/lang/Exception
         393   397   460   Class java/lang/Exception
         410   415   460   Class java/lang/Exception
         418   425   460   Class java/lang/Exception
         428   444   460   Class java/lang/Exception
         500   503  2010   Class org/json/JSONException
         507   515  2010   Class org/json/JSONException
         518   547  2010   Class org/json/JSONException
         548   551  2010   Class org/json/JSONException
         555   591  2010   Class org/json/JSONException
         592   598  2010   Class org/json/JSONException
         601   605  2010   Class org/json/JSONException
         608   613  2010   Class org/json/JSONException
         625   650  2010   Class org/json/JSONException
         652   658  2010   Class org/json/JSONException
         664   667  2010   Class org/json/JSONException
         679   684  2010   Class org/json/JSONException
         686   689  2010   Class org/json/JSONException
         692   731  2010   Class org/json/JSONException
         734   749  2010   Class org/json/JSONException
         752   757  2010   Class org/json/JSONException
         760   773  2010   Class org/json/JSONException
         776   790  2010   Class org/json/JSONException
         793   798  2010   Class org/json/JSONException
         801   824  2010   Class org/json/JSONException
         830   835  2010   Class org/json/JSONException
         855   863  2010   Class org/json/JSONException
         866   874  2010   Class org/json/JSONException
         877   885  2010   Class org/json/JSONException
         888   906  2010   Class org/json/JSONException
         909   915  2010   Class org/json/JSONException
         919   924  2010   Class org/json/JSONException
         931   935  2010   Class org/json/JSONException
         940   995  2010   Class org/json/JSONException
         997  1000  2010   Class org/json/JSONException
        1004  1014  2010   Class org/json/JSONException
        1017  1020  1053   Class java/lang/Exception
        1024  1035  1053   Class java/lang/Exception
        1035  1038  1045   Class java/lang/Exception
        1061  1065  2010   Class org/json/JSONException
        1073  1080  2010   Class org/json/JSONException
        1085  1092  2010   Class org/json/JSONException
        1101  1108  2010   Class org/json/JSONException
        1111  1125  2010   Class org/json/JSONException
        1127  1133  2010   Class org/json/JSONException
        1135  1140  2010   Class org/json/JSONException
        1148  1153  2010   Class org/json/JSONException
        1157  1164  2010   Class org/json/JSONException
        1166  1170  2010   Class org/json/JSONException
        1178  1182  2010   Class org/json/JSONException
        1185  1194  2010   Class org/json/JSONException
        1196  1203  2010   Class org/json/JSONException
        1206  1216  2010   Class org/json/JSONException
        1219  1222  2010   Class org/json/JSONException
        1237  1249  2010   Class org/json/JSONException
        1253  1258  2010   Class org/json/JSONException
        1259  1269  2010   Class org/json/JSONException
        1275  1282  2010   Class org/json/JSONException
        1290  1296  2010   Class org/json/JSONException
        1299  1312  2010   Class org/json/JSONException
        1314  1320  2010   Class org/json/JSONException
        1322  1327  2010   Class org/json/JSONException
        1335  1340  2010   Class org/json/JSONException
        1344  1351  2010   Class org/json/JSONException
        1353  1357  2010   Class org/json/JSONException
        1365  1369  2010   Class org/json/JSONException
        1372  1381  2010   Class org/json/JSONException
        1383  1390  2010   Class org/json/JSONException
        1393  1403  2010   Class org/json/JSONException
        1406  1409  2010   Class org/json/JSONException
        1431  1443  2010   Class org/json/JSONException
        1450  1474  2010   Class org/json/JSONException
        1478  1483  2010   Class org/json/JSONException
        1484  1496  2010   Class org/json/JSONException
        1503  1511  2010   Class org/json/JSONException
        1519  1525  2010   Class org/json/JSONException
        1528  1534  2010   Class org/json/JSONException
        1537  1543  2010   Class org/json/JSONException
        1546  1555  2010   Class org/json/JSONException
        1557  1564  2010   Class org/json/JSONException
        1569  1576  2010   Class org/json/JSONException
        1578  1587  2010   Class org/json/JSONException
        1590  1595  2010   Class org/json/JSONException
        1600  1603  2010   Class org/json/JSONException
        1608  1627  2010   Class org/json/JSONException
        1629  1636  2010   Class org/json/JSONException
        1639  1649  2010   Class org/json/JSONException
        1652  1655  2010   Class org/json/JSONException
        1670  1682  2010   Class org/json/JSONException
        1686  1696  2010   Class org/json/JSONException
        1699  1704  2010   Class org/json/JSONException
        1708  1720  2010   Class org/json/JSONException
        1724  1731  2010   Class org/json/JSONException
        1737  1745  2010   Class org/json/JSONException
        1746  1756  2010   Class org/json/JSONException
        1757  1762  2010   Class org/json/JSONException
        1765  1768  2010   Class org/json/JSONException
        1772  1787  2010   Class org/json/JSONException
        1788  1802  2010   Class org/json/JSONException
        1803  1806  2010   Class org/json/JSONException
        1807  1818  2010   Class org/json/JSONException
        1820  1841  2010   Class org/json/JSONException
        1842  1872  2010   Class org/json/JSONException
        1873  1907  2010   Class org/json/JSONException
        1908  1935  2010   Class org/json/JSONException
        1938  1941  2010   Class org/json/JSONException
        1942  1975  2010   Class org/json/JSONException
        1976  2003  2010   Class org/json/JSONException
    LineNumberTable:
      line 2: 2
      line 3: 5
      line 4: 9
      line 7: 13
      line 8: 17
      line 9: 43
      line 14: 47
      line 18: 56
      line 20: 62
      line 21: 91
      line 23: 108
      line 24: 121
      line 25: 129
      line 26: 133
      line 27: 146
      line 28: 154
      line 31: 160
      line 34: 184
      line 40: 235
      line 41: 243
      line 42: 250
      line 56: 256
      line 57: 262
      line 58: 291
      line 60: 308
      line 61: 321
      line 62: 329
      line 63: 333
      line 64: 346
      line 65: 352
      line 66: 364
      line 72: 370
      line 75: 394
      line 81: 445
      line 82: 453
      line 83: 460
      line 97: 466
      line 98: 477
      line 99: 488
      line 103: 500
      line 104: 544
      line 106: 548
      line 107: 588
      line 109: 592
      line 110: 635
      line 112: 647
      line 113: 655
      line 115: 666
      line 116: 686
      line 117: 703
      line 118: 722
      line 119: 728
      line 120: 746
      line 121: 764
      line 123: 770
      line 124: 787
      line 125: 805
      line 127: 815
      line 129: 833
      line 131: 903
      line 132: 912
      line 134: 921
      line 139: 932
      line 143: 944
      line 146: 955
      line 147: 970
      line 148: 987
      line 152: 997
      line 153: 1011
      line 155: 1017
      line 156: 1035
      line 158: 1062
      line 163: 1074
      line 165: 1086
      line 167: 1105
      line 168: 1115
      line 169: 1119
      line 170: 1127
      line 171: 1137
      line 172: 1161
      line 173: 1167
      line 175: 1179
      line 176: 1191
      line 177: 1219
      line 178: 1239
      line 181: 1255
      line 182: 1263
      line 188: 1276
      line 190: 1293
      line 191: 1302
      line 192: 1306
      line 193: 1314
      line 194: 1324
      line 195: 1348
      line 196: 1354
      line 198: 1366
      line 199: 1378
      line 200: 1406
      line 202: 1435
      line 203: 1440
      line 206: 1454
      line 207: 1459
      line 209: 1464
      line 212: 1480
      line 213: 1486
      line 220: 1505
      line 222: 1522
      line 223: 1531
      line 224: 1537
      line 225: 1549
      line 226: 1557
      line 228: 1573
      line 229: 1592
      line 230: 1624
      line 231: 1652
      line 232: 1672
      line 235: 1688
      line 236: 1701
      line 237: 1710
      line 239: 1728
      line 247: 1739
      line 248: 1748
      line 249: 1759
      line 251: 1765
      line 252: 1778
      line 253: 1791
      line 254: 1796
      line 257: 1803
      line 258: 1838
      line 259: 1869
      line 261: 1900
      line 262: 1932
      line 263: 1938
      line 266: 1972
      line 271: 2003
      line 272: 2013

  public static int a(ai.guiji.duix.sdk.client.loader.ModelInfo$Frame);
    Code:
       0: aload_0
       1: getfield      #231                // Field ai/guiji/duix/sdk/client/loader/ModelInfo$Frame.index:I
       4: ireturn
    LineNumberTable:
      line 273: 1

  public static void a(android.content.Context);
    Code:
       0: new           #441                // class a/b
       3: dup
       4: aload_0
       5: invokespecial #443                // Method a/b."<init>":(Landroid/content/Context;)V
       8: invokevirtual #445                // Method a/b.run:()V
      11: return
    LineNumberTable:
      line 1: 0

  public static {};
    Code:
       0: new           #94                 // class java/util/HashMap
       3: dup
       4: dup
       5: astore_0
       6: invokespecial #447                // Method java/util/HashMap."<init>":()V
       9: putstatic     #92                 // Field a:Ljava/util/HashMap;
      12: new           #94                 // class java/util/HashMap
      15: dup
      16: dup2
      17: dup2
      18: astore_1
      19: aload_0
      20: dup
      21: dup
      22: dup2
      23: aload_1
      24: dup
      25: invokespecial #447                // Method java/util/HashMap."<init>":()V
      28: putstatic     #157                // Field b:Ljava/util/HashMap;
      31: invokestatic  #453                // Method java/util/concurrent/Executors.newSingleThreadExecutor:()Ljava/util/concurrent/ExecutorService;
      34: putstatic     #31                 // Field c:Ljava/util/concurrent/ExecutorService;
      37: ldc_w         #455                // String alpha_model.b
      40: ldc_w         #457                // String ab
      43: invokevirtual #461                // Method java/util/HashMap.put:(Ljava/lang/Object;Ljava/lang/Object;)Ljava/lang/Object;
      46: pop
      47: ldc_w         #463                // String alpha_model.p
      50: ldc_w         #465                // String ap
      53: invokevirtual #461                // Method java/util/HashMap.put:(Ljava/lang/Object;Ljava/lang/Object;)Ljava/lang/Object;
      56: pop
      57: ldc_w         #467                // String cacert.p
      60: ldc_w         #469                // String cp
      63: invokevirtual #461                // Method java/util/HashMap.put:(Ljava/lang/Object;Ljava/lang/Object;)Ljava/lang/Object;
      66: pop
      67: ldc           #159                // String weight_168u.b
      69: ldc_w         #433                // String wb
      72: invokevirtual #461                // Method java/util/HashMap.put:(Ljava/lang/Object;Ljava/lang/Object;)Ljava/lang/Object;
      75: pop
      76: ldc_w         #471                // String wenet.o
      79: ldc_w         #417                // String wo
      82: invokevirtual #461                // Method java/util/HashMap.put:(Ljava/lang/Object;Ljava/lang/Object;)Ljava/lang/Object;
      85: pop
      86: ldc_w         #473                // String dh_model.b
      89: ldc_w         #423                // String db
      92: invokevirtual #461                // Method java/util/HashMap.put:(Ljava/lang/Object;Ljava/lang/Object;)Ljava/lang/Object;
      95: pop
      96: ldc_w         #475                // String dh_model.p
      99: ldc_w         #428                // String dp
     102: invokevirtual #461                // Method java/util/HashMap.put:(Ljava/lang/Object;Ljava/lang/Object;)Ljava/lang/Object;
     105: pop
     106: ldc           #173                // String bbox.j
     108: ldc_w         #477                // String bj
     111: invokevirtual #461                // Method java/util/HashMap.put:(Ljava/lang/Object;Ljava/lang/Object;)Ljava/lang/Object;
     114: pop
     115: ldc           #185                // String config.j
     117: ldc_w         #479                // String cj
     120: invokevirtual #461                // Method java/util/HashMap.put:(Ljava/lang/Object;Ljava/lang/Object;)Ljava/lang/Object;
     123: pop
     124: ldc           #159                // String weight_168u.b
     126: ldc_w         #433                // String wb
     129: invokevirtual #461                // Method java/util/HashMap.put:(Ljava/lang/Object;Ljava/lang/Object;)Ljava/lang/Object;
     132: pop
     133: return
    LineNumberTable:
      line 1: 0
      line 2: 12
      line 3: 31
      line 6: 37
      line 7: 47
      line 8: 57
      line 9: 67
      line 10: 76
      line 12: 86
      line 13: 96
      line 14: 106
      line 15: 115
      line 16: 124
}
